autocommitmessage/__init__.py
autocommitmessage/commit_generator.py
autocommitmessage/llm.py
autocommitmessage/prompts.py
autocommitmessage-0.1.4.dist-info/licenses/LICENSE
autocommitmessage-0.1.4.dist-info/METADATA
autocommitmessage-0.1.4.dist-info/WHEEL
autocommitmessage-0.1.4.dist-info/entry_points.txt
autocommitmessage-0.1.4.dist-info/top_level.txt
autocommitmessage-0.1.4.dist-info/RECORD
