Metadata-Version: 2.4
Name: autocommitmessage
Version: 0.1.4
Summary: A tool to automatically generate git commit messages using an LLM.
Author-email: SLPRYSQUID <coleseto123@gmail.com>
License: MIT License
Project-URL: Homepage, https://github.com/slipperysquid/AutoCommitMessage
Project-URL: Bug Tracker, https://github.com/slipperysquid/AutoCommitMessage/issues
Classifier: Programming Language :: Python :: 3
Classifier: License :: OSI Approved :: MIT License
Classifier: Operating System :: OS Independent
Requires-Python: >=3.8
License-File: LICENSE
Requires-Dist: GitPython>=3.1.45
Requires-Dist: langchain>=0.3.27
Requires-Dist: langchain-google-genai>=2.1.10
Requires-Dist: langsmith>=0.4.27
Requires-Dist: python-dotenv>=0.9.9
Provides-Extra: dev
Requires-Dist: pytest>=8.4.2; extra == "dev"
Requires-Dist: pytest-mock>=3.15.0; extra == "dev"
Dynamic: license-file
